relations_rest.py
relations_rest-0.5.0.dist-info/LICENSE.txt
relations_rest-0.5.0.dist-info/METADATA
relations_rest-0.5.0.dist-info/WHEEL
relations_rest-0.5.0.dist-info/top_level.txt
relations_rest-0.5.0.dist-info/RECORD
