Metadata-Version: 2.1
Name: relations-rest
Version: 0.5.0
Summary: API Modeling through REST
Home-page: https://github.com/relations-dil/python-relations-rest
Author: Gaffer Fitch
Author-email: relations@gaf3.com
Classifier: Programming Language :: Python :: 3
Classifier: License :: OSI Approved :: MIT License
License-File: LICENSE.txt
Requires-Dist: requests (==2.25.1)
Requires-Dist: relations-dil (==0.6.12)
